statswalespy/__init__.py
statswalespy/check_internet_connection.py
statswalespy/download_data.py
statswalespy/search.py
statswalespy-0.1.2.dist-info/LICENSE.txt
statswalespy-0.1.2.dist-info/METADATA
statswalespy-0.1.2.dist-info/WHEEL
statswalespy-0.1.2.dist-info/top_level.txt
statswalespy-0.1.2.dist-info/RECORD
