Metadata-Version: 2.1
Name: statswalespy
Version: 0.1.2
Summary: A Python package for downloading data and metadata from the StatsWales API.
Home-page: https://github.com/josephlewisjgl/statswalespy
Author: Joe Lewis, Jamie Ralph
Author-email: josephgeorgelewis2000@gmail.com
License: MIT
Keywords: Wales,statswales,Welsh
Platform: UNKNOWN
Classifier: Development Status :: 4 - Beta
Classifier: Intended Audience :: Developers
Classifier: Topic :: Software Development :: Build Tools
Classifier: License :: OSI Approved :: MIT License
Classifier: Programming Language :: Python :: 3
Classifier: Programming Language :: Python :: 3.4
Classifier: Programming Language :: Python :: 3.5
Classifier: Programming Language :: Python :: 3.6
Requires-Dist: pandas
Requires-Dist: requests
